pytest_examples/__init__.py
pytest_examples/config.py
pytest_examples/eval_example.py
pytest_examples/find_examples.py
pytest_examples/lint.py
pytest_examples/modify_files.py
pytest_examples/py.typed
pytest_examples/run_code.py
pytest_examples/traceback.py
pytest_examples-0.0.18.dist-info/METADATA
pytest_examples-0.0.18.dist-info/WHEEL
pytest_examples-0.0.18.dist-info/entry_points.txt
pytest_examples-0.0.18.dist-info/licenses/LICENSE
pytest_examples-0.0.18.dist-info/RECORD
