Metadata-Version: 2.4
Name: pytest-examples
Version: 0.0.18
Summary: Pytest plugin for testing examples in docstrings and markdown files.
Project-URL: repository, https://github.com/pydantic/pytest-examples
Author-email: Samuel Colvin <s@muelcolvin.com>
License-Expression: MIT
License-File: LICENSE
Classifier: Environment :: Console
Classifier: Environment :: MacOS X
Classifier: Framework :: Pytest
Classifier: Intended Audience :: Developers
Classifier: License :: OSI Approved :: MIT License
Classifier: Operating System :: POSIX :: Linux
Classifier: Operating System :: Unix
Classifier: Programming Language :: Python
Classifier: Programming Language :: Python :: 3
Classifier: Programming Language :: Python :: 3 :: Only
Classifier: Programming Language :: Python :: 3.8
Classifier: Programming Language :: Python :: 3.9
Classifier: Programming Language :: Python :: 3.10
Classifier: Programming Language :: Python :: 3.11
Classifier: Programming Language :: Python :: 3.12
Classifier: Programming Language :: Python :: 3.13
Classifier: Topic :: Software Development :: Libraries :: Python Modules
Requires-Python: >=3.8
Requires-Dist: black>=23
Requires-Dist: pytest>=7
Requires-Dist: ruff>=0.5.0
